rouleur
