Metadata-Version: 1.1
Name: rouleur
Version: 0.0.3
Summary: Cycling performance modelling with Python
Home-page: https://github.com/jmackie4/rouleur
Author: Jordan Mackie
Author-email: jmackie@protonmail.com
License: MIT
Keywords: cycling power modelling
Platform: UNKNOWN
Classifier: Development Status :: 3 - Alpha
Classifier: Intended Audience :: Science/Research
Classifier: Topic :: Scientific/Engineering :: Physics
Classifier: License :: OSI Approved :: MIT License
Classifier: Programming Language :: Python :: 3.5
